temp_index.py
temp_index-0.3.0.dist-info/WHEEL
temp_index-0.3.0.dist-info/METADATA
temp_index-0.3.0.dist-info/RECORD
